koolbox/__init__.py
koolbox/models/sequential_feature_selector.py
koolbox/models/validators.py
koolbox/models/weighted_ensemble_classifier.py
koolbox/models/weighted_ensemble_regressor.py
koolbox/trainer/base.py
koolbox/trainer/trainer.py
koolbox/trainer/validator.py
koolbox-0.1.3.dist-info/licenses/LICENSE
koolbox-0.1.3.dist-info/METADATA
koolbox-0.1.3.dist-info/WHEEL
koolbox-0.1.3.dist-info/top_level.txt
koolbox-0.1.3.dist-info/RECORD
