Metadata-Version: 2.4
Name: koolbox
Version: 0.1.3
Summary: A collection of utility functions designed to simplify training machine learning models for Kaggle competitions.
Author: Mahdi Ravaghi
Maintainer: Mahdi Ravaghi
License: Apache Software License 2.0
Project-URL: Homepage, https://github.com/ravaghi/koolbox
Project-URL: Bug Tracker, https://github.com/ravaghi/koolbox/issues
Project-URL: Documentation, https://github.com/ravaghi/koolbox#readme
Project-URL: Repository, https://github.com/ravaghi/koolbox.git
Keywords: machine-learning,kaggle,training,cross-validation,model-evaluation
Classifier: Intended Audience :: Science/Research
Classifier: Intended Audience :: Developers
Classifier: Programming Language :: Python :: 3
Classifier: Programming Language :: Python :: 3.7
Classifier: Programming Language :: Python :: 3.8
Classifier: Programming Language :: Python :: 3.9
Classifier: Programming Language :: Python :: 3.10
Classifier: Programming Language :: Python :: 3.11
Classifier: License :: OSI Approved :: Apache Software License
Classifier: Operating System :: OS Independent
Classifier: Topic :: Scientific/Engineering :: Artificial Intelligence
Classifier: Topic :: Scientific/Engineering :: Information Analysis
Requires-Python: >=3.7
License-File: LICENSE
Requires-Dist: scikit-learn>=1.5.2
Requires-Dist: optuna>=4.2.1
Requires-Dist: pandas>=2.2.3
Requires-Dist: numpy>=1.26.4
Dynamic: license-file
